RemoveWindowsLockScreenAds/RemoveWindowsLockScreenAds.py
RemoveWindowsLockScreenAds/__init__.py
RemoveWindowsLockScreenAds/__main__.py
RemoveWindowsLockScreenAds-0.5.1.dist-info/LICENSE
RemoveWindowsLockScreenAds-0.5.1.dist-info/METADATA
RemoveWindowsLockScreenAds-0.5.1.dist-info/WHEEL
RemoveWindowsLockScreenAds-0.5.1.dist-info/top_level.txt
RemoveWindowsLockScreenAds-0.5.1.dist-info/RECORD
