Metadata-Version: 2.1
Name: RemoveWindowsLockScreenAds
Version: 0.5.1
Summary: Remove Windows lock screen ads/Spotlight ads while keeping the rotating Spotlight image backgrounds.
Author-email: Branden Clark <clark@rpis.ec>
License: MIT
Project-URL: Homepage, https://github.com/clarkb7/RemoveWindowsLockScreenAds
Project-URL: Bug Tracker, https://github.com/clarkb7/RemoveWindowsLockScreenAds/issues
Keywords: windows-spotlight,remove-ads,windows-lockscreen
Classifier: Development Status :: 4 - Beta
Classifier: Operating System :: Microsoft :: Windows :: Windows 10
Classifier: Intended Audience :: End Users/Desktop
Classifier: License :: OSI Approved :: MIT License
Classifier: Natural Language :: English
Classifier: Programming Language :: Python :: 3 :: Only
Classifier: Topic :: Utilities
Requires-Python: >=3.7
License-File: LICENSE
Requires-Dist: pywin32
